{
    "SPDXID": "SPDXRef-DOCUMENT",
    "spdxVersion": "SPDX-2.3",
    "creationInfo": {
        "created": "2023-12-07T10:59:11Z",
        "creators": [
            "Tool: GitHub.com-Dependency-Graph"
        ],
        "comment": "Exact versions could not be resolved for some packages. For more information: https://docs.github.com/en/code-security/supply-chain-security/understanding-your-software-supply-chain/about-the-dependency-graph#dependencies-included."
    },
    "name": "com.github.documentcloud/jammit",
    "dataLicense": "CC0-1.0",
    "documentDescribes": [
        "SPDXRef-com.github.documentcloud-jammit"
    ],
    "documentNamespace": "https://github.com/documentcloud/jammit/dependency_graph/sbom-6f94fffa248408b4",
    "packages": [
        {
            "SPDXID": "SPDXRef-com.github.documentcloud-jammit",
            "name": "com.github.documentcloud/jammit",
            "versionInfo": "",
            "downloadLocation": "git+https://github.com/documentcloud/jammit",
            "licenseDeclared": "MIT",
            "filesAnalyzed": false,
            "supplier": "NOASSERTION",
            "externalRefs": [
                {
                    "referenceCategory": "PACKAGE-MANAGER",
                    "referenceType": "purl",
                    "referenceLocator": "pkg:github/documentcloud/jammit"
                }
            ]
        },
        {
            "SPDXID": "SPDXRef-rubygems-closure-compiler",
            "name": "rubygems:closure-compiler",
            "versionInfo": "~> 1.1",
            "downloadLocation": "NOASSERTION",
            "filesAnalyzed": false,
            "supplier": "NOASSERTION"
        },
        {
            "SPDXID": "SPDXRef-rubygems-cssmin",
            "name": "rubygems:cssmin",
            "versionInfo": "~> 1.0",
            "downloadLocation": "NOASSERTION",
            "filesAnalyzed": false,
            "supplier": "NOASSERTION"
        },
        {
            "SPDXID": "SPDXRef-rubygems-jsmin",
            "name": "rubygems:jsmin",
            "versionInfo": "~> 1.0",
            "downloadLocation": "NOASSERTION",
            "filesAnalyzed": false,
            "supplier": "NOASSERTION"
        },
        {
            "SPDXID": "SPDXRef-rubygems-pry",
            "name": "rubygems:pry",
            "versionInfo": ">= 0",
            "downloadLocation": "NOASSERTION",
            "filesAnalyzed": false,
            "supplier": "NOASSERTION"
        },
        {
            "SPDXID": "SPDXRef-rubygems-rails",
            "name": "rubygems:rails",
            "versionInfo": "~> 5.0",
            "downloadLocation": "NOASSERTION",
            "filesAnalyzed": false,
            "supplier": "NOASSERTION"
        },
        {
            "SPDXID": "SPDXRef-rubygems-rake",
            "name": "rubygems:rake",
            "versionInfo": "~> 10.3",
            "downloadLocation": "NOASSERTION",
            "filesAnalyzed": false,
            "supplier": "NOASSERTION"
        },
        {
            "SPDXID": "SPDXRef-rubygems-RedCloth",
            "name": "rubygems:RedCloth",
            "versionInfo": "~> 4.2",
            "downloadLocation": "NOASSERTION",
            "filesAnalyzed": false,
            "supplier": "NOASSERTION"
        },
        {
            "SPDXID": "SPDXRef-rubygems-sass",
            "name": "rubygems:sass",
            "versionInfo": "~> 3.4",
            "downloadLocation": "NOASSERTION",
            "filesAnalyzed": false,
            "supplier": "NOASSERTION"
        },
        {
            "SPDXID": "SPDXRef-rubygems-uglifier",
            "name": "rubygems:uglifier",
            "versionInfo": "~> 2.5",
            "downloadLocation": "NOASSERTION",
            "filesAnalyzed": false,
            "supplier": "NOASSERTION"
        },
        {
            "SPDXID": "SPDXRef-rubygems-yui-compressor",
            "name": "rubygems:yui-compressor",
            "versionInfo": "~> 0.12",
            "downloadLocation": "NOASSERTION",
            "filesAnalyzed": false,
            "supplier": "NOASSERTION"
        }
    ],
    "relationships": [
        {
            "relationshipType": "DEPENDS_ON",
            "spdxElementId": "SPDXRef-com.github.documentcloud-jammit",
            "relatedSpdxElement": "SPDXRef-rubygems-closure-compiler"
        },
        {
            "relationshipType": "DEPENDS_ON",
            "spdxElementId": "SPDXRef-com.github.documentcloud-jammit",
            "relatedSpdxElement": "SPDXRef-rubygems-cssmin"
        },
        {
            "relationshipType": "DEPENDS_ON",
            "spdxElementId": "SPDXRef-com.github.documentcloud-jammit",
            "relatedSpdxElement": "SPDXRef-rubygems-jsmin"
        },
        {
            "relationshipType": "DEPENDS_ON",
            "spdxElementId": "SPDXRef-com.github.documentcloud-jammit",
            "relatedSpdxElement": "SPDXRef-rubygems-pry"
        },
        {
            "relationshipType": "DEPENDS_ON",
            "spdxElementId": "SPDXRef-com.github.documentcloud-jammit",
            "relatedSpdxElement": "SPDXRef-rubygems-rails"
        },
        {
            "relationshipType": "DEPENDS_ON",
            "spdxElementId": "SPDXRef-com.github.documentcloud-jammit",
            "relatedSpdxElement": "SPDXRef-rubygems-rake"
        },
        {
            "relationshipType": "DEPENDS_ON",
            "spdxElementId": "SPDXRef-com.github.documentcloud-jammit",
            "relatedSpdxElement": "SPDXRef-rubygems-RedCloth"
        },
        {
            "relationshipType": "DEPENDS_ON",
            "spdxElementId": "SPDXRef-com.github.documentcloud-jammit",
            "relatedSpdxElement": "SPDXRef-rubygems-sass"
        },
        {
            "relationshipType": "DEPENDS_ON",
            "spdxElementId": "SPDXRef-com.github.documentcloud-jammit",
            "relatedSpdxElement": "SPDXRef-rubygems-uglifier"
        },
        {
            "relationshipType": "DEPENDS_ON",
            "spdxElementId": "SPDXRef-com.github.documentcloud-jammit",
            "relatedSpdxElement": "SPDXRef-rubygems-yui-compressor"
        }
    ]
}