{
  "files": [
    {
      "fileName": "./net7.0/App.dll",
      "SPDXID": "SPDXRef-File--net7.0-App.dll-07F920821E1440B33DB0507973C30A24184FB832",
      "checksums": [
        {
          "algorithm": "SHA256",
          "checksumValue": "d7bc98fcc4954892353994cf0f42b95c3d9fca5ea51857be27f9b6b890d22639"
        },
        {
          "algorithm": "SHA1",
          "checksumValue": "07f920821e1440b33db0507973c30a24184fb832"
        }
      ],
      "licenseConcluded": "NOASSERTION",
      "licenseInfoInFiles": [
        "NOASSERTION"
      ],
      "copyrightText": "NOASSERTION"
    },
    {
      "fileName": "./net6.0/App.dll",
      "SPDXID": "SPDXRef-File--net6.0-App.dll-758D08D6F1D0F05B720BD18E0842E3E2E62AB2D0",
      "checksums": [
        {
          "algorithm": "SHA256",
          "checksumValue": "26553234ce4688863ed920b999decb0ea535754039c149f57e043d3cc2b06719"
        },
        {
          "algorithm": "SHA1",
          "checksumValue": "758d08d6f1d0f05b720bd18e0842e3e2e62ab2d0"
        }
      ],
      "licenseConcluded": "NOASSERTION",
      "licenseInfoInFiles": [
        "NOASSERTION"
      ],
      "copyrightText": "NOASSERTION"
    },
    {
      "fileName": "./net6.0/App.deps.json",
      "SPDXID": "SPDXRef-File--net6.0-App.deps.json-CC39C74BA343901DAB07D73041C2DE4183B2A1A9",
      "checksums": [
        {
          "algorithm": "SHA256",
          "checksumValue": "3ab801943e51c8b1c714149e3d6d77f4101f4d3a7a57395b7dfcbfa7afb92c38"
        },
        {
          "algorithm": "SHA1",
          "checksumValue": "cc39c74ba343901dab07d73041c2de4183b2a1a9"
        }
      ],
      "licenseConcluded": "NOASSERTION",
      "licenseInfoInFiles": [
        "NOASSERTION"
      ],
      "copyrightText": "NOASSERTION"
    },
    {
      "fileName": "./net8.0/App.runtimeconfig.json",
      "SPDXID": "SPDXRef-File--net8.0-App.runtimeconfig.json-03B9744E89327431A619505A7C72FD497783D884",
      "checksums": [
        {
          "algorithm": "SHA256",
          "checksumValue": "28329cf08f6505e73806b17558b187c02f0c1c516fe47ebfb7a013d082aaa306"
        },
        {
          "algorithm": "SHA1",
          "checksumValue": "03b9744e89327431a619505a7c72fd497783d884"
        }
      ],
      "licenseConcluded": "NOASSERTION",
      "licenseInfoInFiles": [
        "NOASSERTION"
      ],
      "copyrightText": "NOASSERTION"
    },
    {
      "fileName": "./net7.0/App.runtimeconfig.json",
      "SPDXID": "SPDXRef-File--net7.0-App.runtimeconfig.json-A480014E50F69E53F77CBEB0C1D200842F9875CD",
      "checksums": [
        {
          "algorithm": "SHA256",
          "checksumValue": "489a92c37422b7e5ce212f9701b7a081d887b895f88b91b000976131f90f823f"
        },
        {
          "algorithm": "SHA1",
          "checksumValue": "a480014e50f69e53f77cbeb0c1d200842f9875cd"
        }
      ],
      "licenseConcluded": "NOASSERTION",
      "licenseInfoInFiles": [
        "NOASSERTION"
      ],
      "copyrightText": "NOASSERTION"
    },
    {
      "fileName": "./net8.0/App.deps.json",
      "SPDXID": "SPDXRef-File--net8.0-App.deps.json-6BDC2FC9577639A3EAB1AE8B2A88D79EC9581D60",
      "checksums": [
        {
          "algorithm": "SHA256",
          "checksumValue": "aa84804132aec0cef118fdea6dc21d0a2d9fb930dd418de057cc88ce91a7ac39"
        },
        {
          "algorithm": "SHA1",
          "checksumValue": "6bdc2fc9577639a3eab1ae8b2a88d79ec9581d60"
        }
      ],
      "licenseConcluded": "NOASSERTION",
      "licenseInfoInFiles": [
        "NOASSERTION"
      ],
      "copyrightText": "NOASSERTION"
    },
    {
      "fileName": "./net8.0/App.dll",
      "SPDXID": "SPDXRef-File--net8.0-App.dll-C01933630625169C53CFC2BF42E8514274EABB51",
      "checksums": [
        {
          "algorithm": "SHA256",
          "checksumValue": "8c49b885380d2120f5fc4ba62a2463b05c7acbd0de748ded287ba6c278f17f48"
        },
        {
          "algorithm": "SHA1",
          "checksumValue": "c01933630625169c53cfc2bf42e8514274eabb51"
        }
      ],
      "licenseConcluded": "NOASSERTION",
      "licenseInfoInFiles": [
        "NOASSERTION"
      ],
      "copyrightText": "NOASSERTION"
    },
    {
      "fileName": "./net7.0/App.deps.json",
      "SPDXID": "SPDXRef-File--net7.0-App.deps.json-38F0D1A4AD2C74948B883C17E6DA064E47C03183",
      "checksums": [
        {
          "algorithm": "SHA256",
          "checksumValue": "3c46e67b1963f6f5b557c30e85e083332852a34b019d26077abc1ec78ddcea34"
        },
        {
          "algorithm": "SHA1",
          "checksumValue": "38f0d1a4ad2c74948b883c17e6da064e47c03183"
        }
      ],
      "licenseConcluded": "NOASSERTION",
      "licenseInfoInFiles": [
        "NOASSERTION"
      ],
      "copyrightText": "NOASSERTION"
    },
    {
      "fileName": "./net6.0/App.runtimeconfig.json",
      "SPDXID": "SPDXRef-File--net6.0-App.runtimeconfig.json-9160A009CB381E044BA4C63E4435DA6BFEB9DC6D",
      "checksums": [
        {
          "algorithm": "SHA256",
          "checksumValue": "ded3aeb5856a11db0b654a785574490cab55839ebfb17efe9e39b89618fc5b91"
        },
        {
          "algorithm": "SHA1",
          "checksumValue": "9160a009cb381e044ba4c63e4435da6bfeb9dc6d"
        }
      ],
      "licenseConcluded": "NOASSERTION",
      "licenseInfoInFiles": [
        "NOASSERTION"
      ],
      "copyrightText": "NOASSERTION"
    }
  ],
  "packages": [
    {
      "name": "Azure Pipelines Hosted Image win22",
      "SPDXID": "SPDXRef-Package-DFF7957EEFBF387F45DD0F076A3EF425F9F6433F08609669B89116D127751087",
      "downloadLocation": "NOASSERTION",
      "filesAnalyzed": false,
      "licenseConcluded": "NOASSERTION",
      "licenseDeclared": "NOASSERTION",
      "copyrightText": "NOASSERTION",
      "versionInfo": "20240729.2.0",
      "externalRefs": [
        {
          "referenceCategory": "PACKAGE-MANAGER",
          "referenceType": "purl",
          "referenceLocator": "https://github.com/actions/virtual-environments"
        }
      ],
      "supplier": "Organization: Microsoft/GitHub"
    },
    {
      "name": "Microsoft.Azure.Functions.DotNetIsolatedNativeHost",
      "SPDXID": "SPDXRef-Package-C9186949124A9703B6BA86384B568DA0F2326EB277EDE9E845148A5AE5D41256",
      "downloadLocation": "NOASSERTION",
      "filesAnalyzed": false,
      "licenseConcluded": "NOASSERTION",
      "licenseDeclared": "NOASSERTION",
      "copyrightText": "NOASSERTION",
      "versionInfo": "1.0.11",
      "externalRefs": [
        {
          "referenceCategory": "PACKAGE-MANAGER",
          "referenceType": "purl",
          "referenceLocator": "pkg:nuget/Microsoft.Azure.Functions.DotNetIsolatedNativeHost@1.0.11"
        }
      ],
      "supplier": "Organization: Microsoft"
    },
    {
      "name": "dotnet-host.official",
      "SPDXID": "SPDXRef-RootPackage",
      "downloadLocation": "NOASSERTION",
      "packageVerificationCode": {
        "packageVerificationCodeValue": "09f4433c8d76a4b44bcf693bff371cf68bc3afd2"
      },
      "filesAnalyzed": true,
      "licenseConcluded": "NOASSERTION",
      "licenseInfoFromFiles": [
        "NOASSERTION"
      ],
      "licenseDeclared": "NOASSERTION",
      "copyrightText": "NOASSERTION",
      "versionInfo": "176102",
      "externalRefs": [
        {
          "referenceCategory": "PACKAGE-MANAGER",
          "referenceType": "purl",
          "referenceLocator": "pkg:swid/Microsoft/sbom.microsoft/dotnet-host.official@176102?tag_id=192aa435-f619-4b11-a56e-561fbf5443bb"
        }
      ],
      "supplier": "Organization: Microsoft",
      "hasFiles": [
        "SPDXRef-File--net7.0-App.runtimeconfig.json-A480014E50F69E53F77CBEB0C1D200842F9875CD",
        "SPDXRef-File--net8.0-App.dll-C01933630625169C53CFC2BF42E8514274EABB51",
        "SPDXRef-File--net8.0-App.deps.json-6BDC2FC9577639A3EAB1AE8B2A88D79EC9581D60",
        "SPDXRef-File--net7.0-App.deps.json-38F0D1A4AD2C74948B883C17E6DA064E47C03183",
        "SPDXRef-File--net6.0-App.runtimeconfig.json-9160A009CB381E044BA4C63E4435DA6BFEB9DC6D",
        "SPDXRef-File--net7.0-App.dll-07F920821E1440B33DB0507973C30A24184FB832",
        "SPDXRef-File--net8.0-App.runtimeconfig.json-03B9744E89327431A619505A7C72FD497783D884",
        "SPDXRef-File--net6.0-App.deps.json-CC39C74BA343901DAB07D73041C2DE4183B2A1A9",
        "SPDXRef-File--net6.0-App.dll-758D08D6F1D0F05B720BD18E0842E3E2E62AB2D0"
      ]
    }
  ],
  "externalDocumentRefs": [],
  "relationships": [
    {
      "relationshipType": "DESCRIBES",
      "relatedSpdxElement": "SPDXRef-RootPackage",
      "spdxElementId": "SPDXRef-DOCUMENT"
    },
    {
      "relationshipType": "DEPENDS_ON",
      "relatedSpdxElement": "SPDXRef-Package-C9186949124A9703B6BA86384B568DA0F2326EB277EDE9E845148A5AE5D41256",
      "spdxElementId": "SPDXRef-RootPackage"
    },
    {
      "relationshipType": "DEPENDS_ON",
      "relatedSpdxElement": "SPDXRef-Package-DFF7957EEFBF387F45DD0F076A3EF425F9F6433F08609669B89116D127751087",
      "spdxElementId": "SPDXRef-RootPackage"
    }
  ],
  "spdxVersion": "SPDX-2.2",
  "dataLicense": "CC0-1.0",
  "SPDXID": "SPDXRef-DOCUMENT",
  "name": "dotnet-host.official 176102",
  "documentNamespace": "https://sbom.microsoft/1:vB_F0XdED0q5n_yQEwCaWA:EOiZPzbDH0SIkoSYMJOtfw/568:176102/0JdoA0KAYEGLwM0o1xU6-Q",
  "creationInfo": {
    "created": "2024-08-08T00:29:20Z",
    "creators": [
      "Organization: Microsoft",
      "Tool: Microsoft.SBOMTool-2.2.6"
    ]
  },
  "documentDescribes": [
    "SPDXRef-RootPackage"
  ]
}