{
 "SPDXID": "SPDXRef-DOCUMENT",
 "name": "ghcr.io/external-secrets/external-secrets@sha256-da1a2ea3f7e855b2fafed792740151edffd7935cfc34542ec6715da30e65ac92",
 "spdxVersion": "SPDX-2.2",
 "creationInfo": {
  "created": "2024-09-25T09:57:29.364262095Z",
  "creators": [
   "Organization: Anchore, Inc",
   "Tool: syft-0.40.1"
  ],
  "licenseListVersion": "3.16"
 },
 "dataLicense": "CC0-1.0",
 "documentNamespace": "https://anchore.com/syft/image/ghcr.io/external-secrets/external-secrets@sha256-da1a2ea3f7e855b2fafed792740151edffd7935cfc34542ec6715da30e65ac92-a74917a1-82b2-4ffd-b521-2d6c356cbf1a",
 "packages": [
  {
   "SPDXID": "SPDXRef-7ae30fdb03dc5c2a",
   "name": "base-files",
   "licenseConcluded": "NOASSERTION",
   "downloadLocation": "NOASSERTION",
   "externalRefs": [
    {
     "referenceCategory": "SECURITY",
     "referenceLocator": "cpe:2.3:a:base-files:base-files:12.4\\+deb12u7:*:*:*:*:*:*:*",
     "referenceType": "cpe23Type"
    },
    {
     "referenceCategory": "SECURITY",
     "referenceLocator": "cpe:2.3:a:base-files:base_files:12.4\\+deb12u7:*:*:*:*:*:*:*",
     "referenceType": "cpe23Type"
    },
    {
     "referenceCategory": "SECURITY",
     "referenceLocator": "cpe:2.3:a:base_files:base-files:12.4\\+deb12u7:*:*:*:*:*:*:*",
     "referenceType": "cpe23Type"
    },
    {
     "referenceCategory": "SECURITY",
     "referenceLocator": "cpe:2.3:a:base_files:base_files:12.4\\+deb12u7:*:*:*:*:*:*:*",
     "referenceType": "cpe23Type"
    },
    {
     "referenceCategory": "SECURITY",
     "referenceLocator": "cpe:2.3:a:base:base-files:12.4\\+deb12u7:*:*:*:*:*:*:*",
     "referenceType": "cpe23Type"
    },
    {
     "referenceCategory": "SECURITY",
     "referenceLocator": "cpe:2.3:a:base:base_files:12.4\\+deb12u7:*:*:*:*:*:*:*",
     "referenceType": "cpe23Type"
    },
    {
     "referenceCategory": "PACKAGE_MANAGER",
     "referenceLocator": "pkg:deb/debian/base-files@12.4+deb12u7?arch=amd64&distro=debian-12",
     "referenceType": "purl"
    }
   ],
   "filesAnalyzed": false,
   "licenseDeclared": "NOASSERTION",
   "originator": "Person: Santiago Vila <sanvila@debian.org>",
   "sourceInfo": "acquired package info from DPKG DB: /var/lib/dpkg/status.d/base-files, /usr/share/doc/base-files/copyright",
   "versionInfo": "12.4+deb12u7"
  },
  {
   "SPDXID": "SPDXRef-acb349e57bdf6c6a",
   "name": "netbase",
   "licenseConcluded": "GPL-2.0",
   "downloadLocation": "NOASSERTION",
   "externalRefs": [
    {
     "referenceCategory": "SECURITY",
     "referenceLocator": "cpe:2.3:a:netbase:netbase:6.4:*:*:*:*:*:*:*",
     "referenceType": "cpe23Type"
    },
    {
     "referenceCategory": "PACKAGE_MANAGER",
     "referenceLocator": "pkg:deb/debian/netbase@6.4?arch=all&distro=debian-12",
     "referenceType": "purl"
    }
   ],
   "filesAnalyzed": false,
   "licenseDeclared": "GPL-2.0",
   "originator": "Person: Marco d'Itri <md@linux.it>",
   "sourceInfo": "acquired package info from DPKG DB: /var/lib/dpkg/status.d/netbase, /usr/share/doc/netbase/copyright",
   "versionInfo": "6.4"
  },
  {
   "SPDXID": "SPDXRef-5ff85e9b6a66f743",
   "name": "tzdata",
   "licenseConcluded": "NOASSERTION",
   "downloadLocation": "NOASSERTION",
   "externalRefs": [
    {
     "referenceCategory": "SECURITY",
     "referenceLocator": "cpe:2.3:a:tzdata:tzdata:2024a-0\\+deb12u1:*:*:*:*:*:*:*",
     "referenceType": "cpe23Type"
    },
    {
     "referenceCategory": "PACKAGE_MANAGER",
     "referenceLocator": "pkg:deb/debian/tzdata@2024a-0+deb12u1?arch=all&distro=debian-12",
     "referenceType": "purl"
    }
   ],
   "filesAnalyzed": false,
   "licenseDeclared": "NOASSERTION",
   "originator": "Person: GNU Libc Maintainers <debian-glibc@lists.debian.org>",
   "sourceInfo": "acquired package info from DPKG DB: /var/lib/dpkg/status.d/tzdata, /usr/share/doc/tzdata/copyright",
   "versionInfo": "2024a-0+deb12u1"
  }
 ]
}
