{
    "SPDXID": "SPDXRef-DOCUMENT",
    "spdxVersion": "SPDX-2.3",
    "creationInfo": {
        "created": "2023-12-07T10:52:22Z",
        "creators": [
            "Tool: GitHub.com-Dependency-Graph"
        ]
    },
    "name": "com.github.mathew-kurian/TextJustify-Android",
    "dataLicense": "CC0-1.0",
    "documentDescribes": [
        "SPDXRef-com.github.mathew-kurian-TextJustify-Android"
    ],
    "documentNamespace": "https://github.com/mathew-kurian/TextJustify-Android/dependency_graph/sbom-14736852b4298398",
    "packages": [
        {
            "SPDXID": "SPDXRef-com.github.mathew-kurian-TextJustify-Android",
            "name": "com.github.mathew-kurian/TextJustify-Android",
            "versionInfo": "",
            "downloadLocation": "git+https://github.com/mathew-kurian/TextJustify-Android",
            "licenseDeclared": "Apache-2.0",
            "filesAnalyzed": false,
            "supplier": "NOASSERTION",
            "externalRefs": [
                {
                    "referenceCategory": "PACKAGE-MANAGER",
                    "referenceType": "purl",
                    "referenceLocator": "pkg:github/mathew-kurian/TextJustify-Android"
                }
            ]
        }
    ],
    "relationships": []
}