{
    "SPDXID": "SPDXRef-DOCUMENT",
    "spdxVersion": "SPDX-2.3",
    "creationInfo": {
        "created": "2023-12-07T11:00:27Z",
        "creators": [
            "Tool: GitHub.com-Dependency-Graph"
        ]
    },
    "name": "com.github.ether/pad",
    "dataLicense": "CC0-1.0",
    "documentDescribes": [
        "SPDXRef-com.github.ether-pad"
    ],
    "documentNamespace": "https://github.com/ether/pad/dependency_graph/sbom-20f88d39171e2ca4",
    "packages": [
        {
            "SPDXID": "SPDXRef-com.github.ether-pad",
            "name": "com.github.ether/pad",
            "versionInfo": "",
            "downloadLocation": "git+https://github.com/ether/pad",
            "filesAnalyzed": false,
            "supplier": "NOASSERTION",
            "externalRefs": [
                {
                    "referenceCategory": "PACKAGE-MANAGER",
                    "referenceType": "purl",
                    "referenceLocator": "pkg:github/ether/pad"
                }
            ]
        }
    ],
    "relationships": []
}