{
    "SPDXID": "SPDXRef-DOCUMENT",
    "spdxVersion": "SPDX-2.3",
    "creationInfo": {
        "created": "2023-12-07T11:00:05Z",
        "creators": [
            "Tool: GitHub.com-Dependency-Graph"
        ]
    },
    "name": "com.github.caged/gitnub",
    "dataLicense": "CC0-1.0",
    "documentDescribes": [
        "SPDXRef-com.github.caged-gitnub"
    ],
    "documentNamespace": "https://github.com/caged/gitnub/dependency_graph/sbom-950ab3983da390a4",
    "packages": [
        {
            "SPDXID": "SPDXRef-com.github.caged-gitnub",
            "name": "com.github.caged/gitnub",
            "versionInfo": "",
            "downloadLocation": "git+https://github.com/caged/gitnub",
            "licenseDeclared": "MIT",
            "filesAnalyzed": false,
            "supplier": "NOASSERTION",
            "externalRefs": [
                {
                    "referenceCategory": "PACKAGE-MANAGER",
                    "referenceType": "purl",
                    "referenceLocator": "pkg:github/caged/gitnub"
                }
            ]
        }
    ],
    "relationships": []
}